otp_auth.py
django_otp_auth-2.3.0.dist-info/METADATA
django_otp_auth-2.3.0.dist-info/WHEEL
django_otp_auth-2.3.0.dist-info/top_level.txt
django_otp_auth-2.3.0.dist-info/RECORD
