Metadata-Version: 2.4
Name: django-otp-auth
Version: 2.3.0
Summary: OTP module for Django
Home-page: https://pypi.org/project/django-otp-auth/
Author: Saurabh Maurya
Author-email: youremail@example.com
Requires-Python: >=3.8
Requires-Dist: requests
Requires-Dist: Django>=3.0
Dynamic: author
Dynamic: author-email
Dynamic: home-page
Dynamic: requires-python
